abra/__init__.py
abra/data.py
abra/session.py
abra/trial.py
abra/utils.py
abra/visualization.py
abra-1.4.2.dist-info/LICENSE
abra-1.4.2.dist-info/METADATA
abra-1.4.2.dist-info/WHEEL
abra-1.4.2.dist-info/top_level.txt
abra-1.4.2.dist-info/RECORD
