Metadata-Version: 2.1
Name: abra
Version: 1.4.2
Summary: abra: open-source eye tracking data analysis
Home-page: https://github.com/abra-eyetracking/abra-eyetracking
Author-email: abra.eyetracking@gmail.com
License: UNKNOWN
Platform: UNKNOWN
Classifier: Programming Language :: Python :: 3
Classifier: License :: OSI Approved :: MIT License
Classifier: Operating System :: OS Independent
Requires-Dist: abra
Requires-Dist: numpy
Requires-Dist: scipy
Requires-Dist: matplotlib
